astunparse/__init__.py
astunparse/__main__.py
astunparse/printer.py
astunparse/unparser.py
astunparse-1.6.2.dist-info/AUTHORS.rst
astunparse-1.6.2.dist-info/LICENSE
astunparse-1.6.2.dist-info/METADATA
astunparse-1.6.2.dist-info/WHEEL
astunparse-1.6.2.dist-info/top_level.txt
astunparse-1.6.2.dist-info/RECORD
