Metadata-Version: 1.2
Name: astunparse
Version: 1.6.2
Summary: An AST unparser for Python
Home-page: https://github.com/simonpercivall/astunparse
Maintainer: Simon Percivall
Maintainer-email: percivall@gmail.com
License: BSD
Keywords: astunparse
Platform: UNKNOWN
Classifier: Development Status :: 5 - Production/Stable
Classifier: Intended Audience :: Developers
Classifier: License :: OSI Approved :: BSD License
Classifier: Natural Language :: English
Classifier: Programming Language :: Python :: 2
Classifier: Programming Language :: Python :: 2.7
Classifier: Programming Language :: Python :: 3
Classifier: Programming Language :: Python :: 3.3
Classifier: Programming Language :: Python :: 3.4
Classifier: Programming Language :: Python :: 3.5
Classifier: Programming Language :: Python :: 3.6
Classifier: Programming Language :: Python :: 3.7
Classifier: Topic :: Software Development :: Code Generators
